Metadata-Version: 1.0
Name: nanatou
Version: 0.0.1
Summary: to my lover
Home-page: UNKNOWN
Author: Kayode Adechinan
Author-email: kayode.adechinan@gmail.com
License: MIT
Platform: UNKNOWN
